sparrow/__init__.py
sparrow/advanced_finetuning.py
sparrow/augment.py
sparrow/config.py
sparrow/integrations.py
sparrow/layers.py
sparrow/utils.py
sparrow_lib-2.0.4.dist-info/LICENSE
sparrow_lib-2.0.4.dist-info/METADATA
sparrow_lib-2.0.4.dist-info/WHEEL
sparrow_lib-2.0.4.dist-info/top_level.txt
sparrow_lib-2.0.4.dist-info/RECORD
