Metadata-Version: 2.2
Name: sparrow-lib
Version: 2.0.4
Summary: A library to augment LLMs with dynamic, trainable routers for efficient fine-tuning.
Home-page: 
Author: AmirReza
Author-email: amirrezaahali@gmail.com
Classifier: Programming Language :: Python :: 3
Classifier: License :: OSI Approved :: MIT License
Classifier: Operating System :: OS Independent
Classifier: Intended Audience :: Developers
Classifier: Topic :: Scientific/Engineering :: Artificial Intelligence
Requires-Python: >=3.7
License-File: LICENSE
Requires-Dist: torch>=1.9.0
Requires-Dist: transformers>=4.10.0
Requires-Dist: pandas
Requires-Dist: scikit-learn
Dynamic: author
Dynamic: author-email
Dynamic: classifier
Dynamic: description
Dynamic: description-content-type
Dynamic: requires-dist
Dynamic: requires-python
Dynamic: summary
